pandemaniac/__init__.py
pandemaniac/sim_viz.py
pandemaniac/visualizer.py
pandemaniac-1.0.4.dist-info/METADATA
pandemaniac-1.0.4.dist-info/WHEEL
pandemaniac-1.0.4.dist-info/top_level.txt
pandemaniac-1.0.4.dist-info/RECORD
