Metadata-Version: 2.1
Name: pandemaniac
Version: 1.0.4
Summary: CS144 Pandemaniac iterative visualizer
Home-page: https://github.com/atisor73/pandemaniac
Author: Rosita Fu
Author-email: rosita.fu99@gmail.com
License: UNKNOWN
Platform: UNKNOWN
Classifier: Programming Language :: Python :: 3
Classifier: Operating System :: OS Independent
Requires-Dist: numpy
Requires-Dist: pandas
Requires-Dist: bokeh (>=2.4.2)
Requires-Dist: panel (>=0.12.6)
Requires-Dist: networkx
Requires-Dist: iqplot
